margarine/__init__.py
margarine/_version.py
margarine/statistics.py
margarine/base/__init__.py
margarine/base/baseflow.py
margarine/estimators/__init__.py
margarine/estimators/clustered.py
margarine/estimators/kde.py
margarine/estimators/nice.py
margarine/estimators/realnvp.py
margarine/utils/__init__.py
margarine/utils/kmeans.py
margarine/utils/utils.py
margarine-2.0.1.dist-info/licenses/LICENSE
margarine-2.0.1.dist-info/METADATA
margarine-2.0.1.dist-info/WHEEL
margarine-2.0.1.dist-info/top_level.txt
margarine-2.0.1.dist-info/RECORD
